src/CLA.v
module CLA(
    input [7:0] a,
    input [7:0] b,
    input cin,
    output [7:0] s,
    output cout,
    output ovf // Overflow flag
);
    wire [7:0] p = a ^ b; //propagate
    wire [7:0] g = a & b; //generate

    wire c1 = g[0] | (p[0] & cin);
    wire c2 = g[1] | (p[1] & g[0]) | (p[1] & p[0] & cin);
    wire c3 = g[2] | (p[2] & g[1]) | (p[2] & p[1] & g[0]) | (p[2] & p[1] & p[0] & cin);
    wire c4 = g[3] | (p[3] & g[2]) | (p[3] & p[2] & g[1]) | (p[3] & p[2] & p[1] & g[0])
     | (p[3] & p[2] & p[1] & p[0] & cin);
    wire c5 = g[4] | (p[4] & g[3]) | (p[4] & p[3] & g[2]) | (p[4] & p[3] & p[2] & g[1])
     | (p[4] & p[3] & p[2] & p[1] & g[0]) | (p[4] & p[3] & p[2] & p[1] & p[0] & cin);
    wire c6 = g[5] | (p[5] & g[4]) | (p[5] & p[4] & g[3]) | (p[5] & p[4] & p[3] & g[2])
     | (p[5] & p[4] & p[3] & p[2] & g[1]) | (p[5] & p[4] & p[3] & p[2] & p[1] & g[0])
     | (p[5] & p[4] & p[3] & p[2] & p[1] & p[0] & cin);
    wire c7 = g[6] | (p[6] & g[5]) | (p[6] & p[5] & g[4]) | (p[6] & p[5] & p[4] & g[3])
     | (p[6] & p[5] & p[4] & p[3] & g[2]) | (p[6] & p[5] & p[4] & p[3] & p[2] & g[1])
     | (p[6] & p[5] & p[4] & p[3] & p[2] & p[1] & g[0]) | (p[6] & p[5] & p[4] & p[3] & p[2] & p[1] & p[0] & cin);
    wire c8 = g[7] | (p[7] & g[6]) | (p[7] & p[6] & g[5]) | (p[7] & p[6] & p[5] & g[4]) | (p[7] & p[6] & p[5] & p[4] & g[3])
     | (p[7] & p[6] & p[5] & p[4] & p[3] & g[2]) | (p[7] & p[6] & p[5] & p[4] & p[3] & p[2] & g[1])
     | (p[7] & p[6] & p[5] & p[4] & p[3] & p[2] & p[1] & g[0]) | (p[7] & p[6] & p[5] & p[4] & p[3] & p[2] & p[1] & p[0] & cin);
    // si = pi xor ci, p is an 8 bit vector
    assign s = p ^ {c7, c6, c5, c4, c3, c2, c1, cin};
    assign cout = c8; // unsigned ovf
    assign ovf = c7 ^ c8; // signed ofv (2s comp max 127)
endmodule

src/alu.v
module alu(
    input [15:0] A,
    input [15:0] B,
    input Ext_cin,
    input [4:0] ALUop,
    output reg [15:0] y,
    output z, // Zero flag
    output n, // Negative flag
    output reg c, // Carry flag
    output reg v // Signed overflow flag
);
    // CLA
    localparam ADD = 5'b00000; // Add
    localparam ADC = 5'b00001; // Add-carry
    localparam SUB = 5'b00010; // Subtract
    localparam SBC = 5'b00011; // Subtract-carry
    localparam AND = 5'b00100; 
    localparam OR = 5'b00101;
    localparam XOR = 5'b00110;
    localparam NOT = 5'b00111;

    localparam LSL = 5'b01000; // Logical shift left
    localparam LSR = 5'b01001; // Logical shift right
    localparam ASR = 5'b01010; // Arithmetic shift right
    localparam ROL = 5'b01011; // Roll left
    localparam ROR = 5'b01100; // Roll right

    // MOV = 5'b01101; // Move
    // LD = 5'b01110; // Load
    // ST = 5'b01111; // Store
    // JMP = 5'b10000; // Jump
    // JZ = 5'b10001; // Jump if zero
    // JC = 5'b10010;
    // ...

    /*
    [15:12] Opcode
    [11:8]  Dest Reg
    [7:4]   Src Reg
    [3:0]   Unused / flags
    */

    wire add_operation = (ALUop==ADD) | (ALUop==ADC);
    wire sub_operation = (ALUop==SUB) | (ALUop==SBC);

    wire Cin_eff = (ALUop==ADD) ? 1'b0 :
                    (ALUop==ADC) ? Ext_cin :
                    (ALUop==SUB) ? 1'b1 :
                    (ALUop==SBC) ? Ext_cin : 1'b0;

    wire [15:0] add_sum;
    wire add_cout;
    wire add_ovf;
   
    wire [7:0] sum_lo, sum_hi;
    wire c_out_lo, c_out_hi;
    wire ovf_lo, ovf_hi;

    CLA a_adder (
        .a   (A[7:0]),
        .b   (B[7:0] ^ {8{sub_operation}}), // bitwise invert if 
        .cin (Cin_eff),
        .s   (sum_lo),
        .cout(c_out_lo),
        .ovf (ovf_lo)  // internal
    );

    CLA b_adder (
        .a   (A[15:8]),
        .b   (B[15:8] ^ {8{sub_operation}}),
        .cin (c_out_lo),   // chain carry
        .s   (sum_hi),
        .cout(c_out_hi),
        .ovf (ovf_hi)
    );

    // Combine outputs
    assign add_sum  = {sum_hi, sum_lo};
    assign add_cout = c_out_hi;

    // For signed overflow: use MSB stage
    assign add_ovf  = ovf_hi;



    always @* begin
        y = 16'h0000;
        c = 1'b0;
        v = 1'b0;

        case(ALUop)
            ADD, ADC: begin
                y = add_sum;
                c = add_cout;
                v = add_ovf;
            end 
            SUB, SBC: begin
                y = add_sum;
                c = add_cout;
                v = add_ovf;
            end
            AND: begin
                y = A & B;
            end
            OR: begin
                y = A | B;
            end
            XOR: begin
                y = A ^ B;
            end
            NOT: begin
                y = ~A;
            end
            LSR: begin
                y = {1'b0, A[15:1]};
                c = A[0];
            end
            LSL: begin
                y = {A[14:0], 1'b0};
                c = A[15];
            end
            ASR: begin
                y = {A[15], A[15:1]};
                c = A[0];
            end
            ROR: begin
                y = {Ext_cin, A[15:1]};
                c = A[0];
            end
            ROL: begin
                y = {A[14:0], Ext_cin};
                c = A[15];
            end
            default: begin
                y = 16'h0000;
            end
        endcase
    end
    assign z = (y == 16'h0000);
    assign n = y[15];
endmodule

tb/tb_alu.v
`timescale 1ps/1ps

module tb_alu;
    reg  [15:0] A, B;
    reg        Ext_cin;
    reg  [4:0] ALUop;
    wire [15:0] y;
    wire       z, n, c, v;

    alu DUT (
        .A(A), .B(B),
        .Ext_cin(Ext_cin),
        .ALUop(ALUop),
        .y(y),
        .z(z),
        .n(n),
        .c(c),
        .v(v),
    );

     initial begin
        $dumpfile("dumpalu.vcd");
        $dumpvars(0, tb_alu);
        /* UPDATE THIS
        // Test ADD
        A=8'd5; B=8'd10; Ext_cin=0; ALUop=4'b0000; #10;
        $display("ADD: 5+10 = %0d, y=%0d c=%b v=%b", A,B,y,c,v);

        // Test SUB
        A=8'd15; B=8'd10; Ext_cin=0; ALUop=4'b0010; #10;
        $display("SUB: 15-10 = %0d, y=%0d c=%b v=%b", A,B,y,c,v);

        // Test AND
        A=8'hF0; B=8'h0F; ALUop=4'b0100; #10;
        $display("AND: F0 & 0F = %h, y=%h", A,B,y);

        // Test OR
        A=8'hF0; B=8'h0F; ALUop=4'b0101; #10;
        $display("OR:  F0 | 0F = %h, y=%h", A,B,y);

        // Test XOR
        A=8'hAA; B=8'h55; ALUop=4'b0110; #10;
        $display("XOR: AA ^ 55 = %h, y=%h", A,B,y);

        // Test NOT
        A=8'h0F; ALUop=4'b0111; #10;
        $display("NOT: ~0F = %h, y=%h", A,y);

        // Test shift
        A=8'b10010001; ALUop=4'b1000; #10; // LSR
        $display("LSR: A=%b, y=%b c=%b", A,y,c);

        A=8'b10010001; ALUop=4'b1001; #10; // LSL
        $display("LSL: A=%b, y=%b c=%b", A,y,c);
        */
        // Done
        $finish;
    end
endmodule

dumpalu.vcd
$date
	Sun Aug 17 20:26:02 2025
$end
$version
	Icarus Verilog
$end
$timescale
	1ps
$end
$scope module tb_alu $end
$var wire 1 ! z $end
$var wire 16 " y [15:0] $end
$var wire 1 # v $end
$var wire 1 $ n $end
$var wire 1 % c $end
$var reg 16 & A [15:0] $end
$var reg 5 ' ALUop [4:0] $end
$var reg 16 ( B [15:0] $end
$var reg 1 ) Ext_cin $end
$scope module DUT $end
$var wire 16 * A [15:0] $end
$var wire 5 + ALUop [4:0] $end
$var wire 16 , B [15:0] $end
$var wire 1 ) Ext_cin $end
$var wire 1 - add_cout $end
$var wire 1 . add_operation $end
$var wire 1 / add_ovf $end
$var wire 1 0 sub_operation $end
$var wire 1 ! z $end
$var wire 8 1 sum_lo [7:0] $end
$var wire 8 2 sum_hi [7:0] $end
$var wire 1 3 ovf_lo $end
$var wire 1 4 ovf_hi $end
$var wire 1 $ n $end
$var wire 1 5 c_out_lo $end
$var wire 1 6 c_out_hi $end
$var wire 16 7 add_sum [15:0] $end
$var wire 1 8 Cin_eff $end
$var parameter 5 9 ADC $end
$var parameter 5 : ADD $end
$var parameter 5 ; AND $end
$var parameter 5 < ASR $end
$var parameter 5 = LSL $end
$var parameter 5 > LSR $end
$var parameter 5 ? NOT $end
$var parameter 5 @ OR $end
$var parameter 5 A ROL $end
$var parameter 5 B ROR $end
$var parameter 5 C SBC $end
$var parameter 5 D SUB $end
$var parameter 5 E XOR $end
$var reg 1 % c $end
$var reg 1 # v $end
$var reg 16 F y [15:0] $end
$scope module a_adder $end
$var wire 8 G a [7:0] $end
$var wire 8 H b [7:0] $end
$var wire 1 I c1 $end
$var wire 1 J c2 $end
$var wire 1 K c3 $end
$var wire 1 L c4 $end
$var wire 1 M c5 $end
$var wire 1 N c6 $end
$var wire 1 O c7 $end
$var wire 1 P c8 $end
$var wire 1 8 cin $end
$var wire 1 5 cout $end
$var wire 8 Q g [7:0] $end
$var wire 1 3 ovf $end
$var wire 8 R p [7:0] $end
$var wire 8 S s [7:0] $end
$upscope $end
$scope module b_adder $end
$var wire 8 T a [7:0] $end
$var wire 8 U b [7:0] $end
$var wire 1 V c1 $end
$var wire 1 W c2 $end
$var wire 1 X c3 $end
$var wire 1 Y c4 $end
$var wire 1 Z c5 $end
$var wire 1 [ c6 $end
$var wire 1 \ c7 $end
$var wire 1 ] c8 $end
$var wire 1 5 cin $end
$var wire 1 6 cout $end
$var wire 8 ^ g [7:0] $end
$var wire 1 4 ovf $end
$var wire 8 _ p [7:0] $end
$var wire 8 ` s [7:0] $end
$upscope $end
$upscope $end
$upscope $end
$enddefinitions $end
$comment Show the parameter values. $end
$dumpall
b110 E
b10 D
b11 C
b1100 B
b1011 A
b101 @
b111 ?
b1001 >
b1000 =
b1010 <
b100 ;
b0 :
b1 9
$end
#0
$dumpvars
b0 `
b0 _
b0 ^
0]
0\
0[
0Z
0Y
0X
0W
0V
b0 U
b0 T
b1111 S
b1111 R
b0 Q
0P
0O
0N
0M
0L
0K
0J
0I
b1010 H
b101 G
b1111 F
08
b1111 7
06
05
04
03
b0 2
b1111 1
00
0/
1.
0-
b1010 ,
b0 +
b101 *
0)
b1010 (
b0 '
b101 &
0%
0$
0#
b1111 "
0!
$end
#10
1%
1V
1W
1X
1Y
1Z
1[
1\
1-
16
1]
15
1P
1O
1N
1M
0$
1I
1K
1L
1J
b0 2
b0 `
b11111111 _
18
b101 7
b101 1
b101 S
b11110101 H
b11111111 U
b11111010 R
b101 Q
0.
10
0!
b101 "
b101 F
b1111 G
b10 '
b10 +
b1111 &
b1111 *
#20
0M
0L
0N
0O
05
0P
0W
0X
0Y
0Z
0[
0\
0-
06
0]
0V
0J
0K
b0 2
b0 `
0I
b0 _
08
b11111111 7
b11111111 1
b11111111 S
b0 U
b1111 H
b11111111 R
b0 Q
00
0%
1!
b0 "
b0 F
b11110000 G
b100 '
b100 +
b1111 (
b1111 ,
b11110000 &
b11110000 *
#30
0!
b11111111 "
b11111111 F
b101 '
b101 +
#40
b0 2
b0 `
0K
0L
0M
0N
0O
05
0P
0J
b11111111 7
b11111111 1
b11111111 S
b1010101 H
b11111111 R
b0 Q
0!
b11111111 "
b11111111 F
b10101010 G
b110 '
b110 +
b1010101 (
b1010101 ,
b10101010 &
b10101010 *
#50
b0 2
b0 `
1J
1K
1L
1M
0N
0O
05
0P
1I
b1100100 7
b1100100 1
b1100100 S
1$
b1011010 R
b101 Q
0!
b1111111111110000 "
b1111111111110000 F
b1111 G
b111 '
b111 +
b1111 &
b1111 *
#60
b1 2
b1 `
15
1P
03
1N
1O
b101010100 7
b1010100 1
b1010100 S
0$
b10101010 R
b1010101 Q
0!
b111111110 "
b111111110 F
b11111111 G
b1000 '
b1000 +
b11111111 &
b11111111 *
#70
05
0P
0-
06
0]
03
0\
0N
0O
0[
0Z
0L
0M
0Y
0X
0J
0K
0W
0V
0I
b1010101 1
b1010101 S
b1111111101010101 7
b11111111 2
b11111111 `
b1010101 R
b0 Q
b11111111 _
0!
b111111110000000 "
b111111110000000 F
b0 G
b11111111 T
b1001 '
b1001 +
b1111111100000000 &
b1111111100000000 *
