src/CLA.v
module CLA(
    input [7:0] a,
    input [7:0] b,
    input cin,
    output [7:0] s,
    output cout,
    output ovf // Overflow flag
);
    wire [7:0] p = a ^ b; //propagate
    wire [7:0] g = a & b; //generate

    wire c1 = g[0] | (p[0] & cin);
    wire c2 = g[1] | (p[1] & g[0]) | (p[1] & p[0] & cin);
    wire c3 = g[2] | (p[2] & g[1]) | (p[2] & p[1] & g[0]) | (p[2] & p[1] & p[0] & cin);
    wire c4 = g[3] | (p[3] & g[2]) | (p[3] & p[2] & g[1]) | (p[3] & p[2] & p[1] & g[0])
     | (p[3] & p[2] & p[1] & p[0] & cin);
    wire c5 = g[4] | (p[4] & g[3]) | (p[4] & p[3] & g[2]) | (p[4] & p[3] & p[2] & g[1])
     | (p[4] & p[3] & p[2] & p[1] & g[0]) | (p[4] & p[3] & p[2] & p[1] & p[0] & cin);
    wire c6 = g[5] | (p[5] & g[4]) | (p[5] & p[4] & g[3]) | (p[5] & p[4] & p[3] & g[2])
     | (p[5] & p[4] & p[3] & p[2] & g[1]) | (p[5] & p[4] & p[3] & p[2] & p[1] & g[0])
     | (p[5] & p[4] & p[3] & p[2] & p[1] & p[0] & cin);
    wire c7 = g[6] | (p[6] & g[5]) | (p[6] & p[5] & g[4]) | (p[6] & p[5] & p[4] & g[3])
     | (p[6] & p[5] & p[4] & p[3] & g[2]) | (p[6] & p[5] & p[4] & p[3] & p[2] & g[1])
     | (p[6] & p[5] & p[4] & p[3] & p[2] & p[1] & g[0]) | (p[6] & p[5] & p[4] & p[3] & p[2] & p[1] & p[0] & cin);
    wire c8 = g[7] | (p[7] & g[6]) | (p[7] & p[6] & g[5]) | (p[7] & p[6] & p[5] & g[4]) | (p[7] & p[6] & p[5] & p[4] & g[3])
     | (p[7] & p[6] & p[5] & p[4] & p[3] & g[2]) | (p[7] & p[6] & p[5] & p[4] & p[3] & p[2] & g[1])
     | (p[7] & p[6] & p[5] & p[4] & p[3] & p[2] & p[1] & g[0]) | (p[7] & p[6] & p[5] & p[4] & p[3] & p[2] & p[1] & p[0] & cin);
    // si = pi xor ci, p is an 8 bit vector
    assign s = p ^ {c7, c6, c5, c4, c3, c2, c1, cin};
    assign cout = c8; // unsigned ovf
    assign ovf = c7 ^ c8; // signed ofv (2s comp max 127)
endmodule

src/alu.v
module alu(
    input [7:0] A,
    input [7:0] B,
    input Ext_cin,
    input [3:0] ALUop,
    output reg [7:0] y,
    output z, // Zero flag
    output n, // Negative flag
    output reg c, // Carry flag
    output reg v, // Signed overflow flag
    output bor
);
    // CLA
    localparam ADD = 4'b0000; // Add
    localparam ADC = 4'b0001; // Add-Carry
    localparam SUB = 4'b0010; // Subtract
    localparam SBC = 4'b0011; // Subtract-Carry

    localparam AND = 4'b0100; // AND
    localparam OR = 4'b0101; // OR
    localparam XOR = 4'b0110; // XOR
    localparam NOT = 4'b0111; // NOT
    localparam LSR = 4'b1000; // Logical shift right
    localparam LSL = 4'b1001; // Logical shift left
    localparam ASR = 4'b1010; // Arithmatic shift right
    //localparam ASL = 4'b1011; // Arithmatic shift left
    localparam ROR = 4'b1100; // Roll right
    localparam ROL = 4'b1101; // Roll left
    localparam PSA = 4'b1110; // Pass A
    localparam PSB = 4'b1111; // Pass B

    wire add_operation = (ALUop==ADD) | (ALUop==ADC);
    wire sub_operation = (ALUop==SUB) | (ALUop==SBC);

    wire [7:0] B_eff = sub_operation ? ~B : B;
    wire Cin_eff = (ALUop==ADD) ? 1'b0 :
                    (ALUop==ADC) ? Ext_cin :
                    (ALUop==SUB) ? 1'b1 :
                    (ALUop==SBC) ? Ext_cin : 1'b0;

    wire [7:0] add_sum;
    wire add_cout;
    wire add_ovf;

    CLA u_adder (
        .a(A),
        .b(B_eff),
        .cin(Cin_eff),
        .s(add_sum),
        .cout(add_cout),
        .ovf(add_ovf)
    );

    always @* begin
        y = 8'h00;
        c = 1'b0;
        v = 1'b0;

        case(ALUop)
            ADD, ADC: begin
                y = add_sum;
                c = add_cout;
                v = add_ovf;
            end 
            SUB, SBC: begin
                y = add_sum;
                c = add_cout;
                v = add_ovf;
            end
            AND: begin
                y = A & B;
            end
            OR: begin
                y = A | B;
            end
            XOR: begin
                y = A ^ B;
            end
            NOT: begin
                y = ~A;
            end
            LSR: begin
                y = {1'b0, A[7:1]};
                c = A[0];
            end
            LSL: begin
                y = {A[6:0], 1'b0};
                c = A[7];
            end
            ASR: begin
                y = {A[7], A[7:1]};
                c = A[0];
            end
            /*ASL: begin
                y = {A[6:0], 1'b0};
                c = A[7];
            end*/
            ROR: begin
                y = {Ext_cin, A[7:1]};
                c = A[0];
            end
            ROL: begin
                y = {A[6:0], Ext_cin};
                c = A[7];
            end
            PSA: y = A;
            PSB: y = B;
            default: begin
                y = 8'h00;
            end
        endcase
    end
    assign bor = sub_operation ? ~add_cout : 1'b0;
    assign z = (y == 8'h00);
    assign n = y[7];
endmodule

tb/tb_alu.v
`timescale 1ps/1ps

module tb_alu;
    reg  [7:0] A, B;
    reg        Ext_cin;
    reg  [3:0] ALUop;
    wire [7:0] y;
    wire       z, n, c, v, bor;

    alu DUT (
        .A(A), .B(B),
        .Ext_cin(Ext_cin),
        .ALUop(ALUop),
        .y(y),
        .z(z),
        .n(n),
        .c(c),
        .v(v),
        .bor(bor)
    );

     initial begin
        $dumpfile("dumpalu.vcd");
        $dumpvars(0, tb_alu);

        // Test ADD
        A=8'd5; B=8'd10; Ext_cin=0; ALUop=4'b0000; #10;
        $display("ADD: 5+10 = %0d, y=%0d c=%b v=%b", A,B,y,c,v);

        // Test SUB
        A=8'd15; B=8'd10; Ext_cin=0; ALUop=4'b0010; #10;
        $display("SUB: 15-10 = %0d, y=%0d c=%b v=%b", A,B,y,c,v);

        // Test AND
        A=8'hF0; B=8'h0F; ALUop=4'b0100; #10;
        $display("AND: F0 & 0F = %h, y=%h", A,B,y);

        // Test OR
        A=8'hF0; B=8'h0F; ALUop=4'b0101; #10;
        $display("OR:  F0 | 0F = %h, y=%h", A,B,y);

        // Test XOR
        A=8'hAA; B=8'h55; ALUop=4'b0110; #10;
        $display("XOR: AA ^ 55 = %h, y=%h", A,B,y);

        // Test NOT
        A=8'h0F; ALUop=4'b0111; #10;
        $display("NOT: ~0F = %h, y=%h", A,y);

        // Test shift
        A=8'b10010001; ALUop=4'b1000; #10; // LSR
        $display("LSR: A=%b, y=%b c=%b", A,y,c);

        A=8'b10010001; ALUop=4'b1001; #10; // LSL
        $display("LSL: A=%b, y=%b c=%b", A,y,c);

        // Done
        $finish;
    end
endmodule

dumpalu.vcd
$date
	Sat Aug 16 21:45:17 2025
$end
$version
	Icarus Verilog
$end
$timescale
	1ps
$end
$scope module tb_alu $end
$var wire 1 ! z $end
$var wire 8 " y [7:0] $end
$var wire 1 # v $end
$var wire 1 $ n $end
$var wire 1 % c $end
$var wire 1 & bor $end
$var reg 8 ' A [7:0] $end
$var reg 4 ( ALUop [3:0] $end
$var reg 8 ) B [7:0] $end
$var reg 1 * Ext_cin $end
$scope module DUT $end
$var wire 8 + A [7:0] $end
$var wire 4 , ALUop [3:0] $end
$var wire 8 - B [7:0] $end
$var wire 1 * Ext_cin $end
$var wire 1 . add_operation $end
$var wire 1 / sub_operation $end
$var wire 1 ! z $end
$var wire 1 $ n $end
$var wire 1 & bor $end
$var wire 8 0 add_sum [7:0] $end
$var wire 1 1 add_ovf $end
$var wire 1 2 add_cout $end
$var wire 1 3 Cin_eff $end
$var wire 8 4 B_eff [7:0] $end
$var parameter 4 5 ADC $end
$var parameter 4 6 ADD $end
$var parameter 4 7 AND $end
$var parameter 4 8 ASR $end
$var parameter 4 9 LSL $end
$var parameter 4 : LSR $end
$var parameter 4 ; NOT $end
$var parameter 4 < OR $end
$var parameter 4 = PSA $end
$var parameter 4 > PSB $end
$var parameter 4 ? ROL $end
$var parameter 4 @ ROR $end
$var parameter 4 A SBC $end
$var parameter 4 B SUB $end
$var parameter 4 C XOR $end
$var reg 1 % c $end
$var reg 1 # v $end
$var reg 8 D y [7:0] $end
$scope module u_adder $end
$var wire 8 E a [7:0] $end
$var wire 8 F b [7:0] $end
$var wire 1 G c1 $end
$var wire 1 H c2 $end
$var wire 1 I c3 $end
$var wire 1 J c4 $end
$var wire 1 K c5 $end
$var wire 1 L c6 $end
$var wire 1 M c7 $end
$var wire 1 N c8 $end
$var wire 1 3 cin $end
$var wire 1 2 cout $end
$var wire 8 O g [7:0] $end
$var wire 1 1 ovf $end
$var wire 8 P p [7:0] $end
$var wire 8 Q s [7:0] $end
$upscope $end
$upscope $end
$upscope $end
$enddefinitions $end
$comment Show the parameter values. $end
$dumpall
b110 C
b10 B
b11 A
b1100 @
b1101 ?
b1111 >
b1110 =
b101 <
b111 ;
b1000 :
b1001 9
b1010 8
b100 7
b0 6
b1 5
$end
#0
$dumpvars
b1111 Q
b1111 P
b0 O
0N
0M
0L
0K
0J
0I
0H
0G
b1010 F
b101 E
b1111 D
b1010 4
03
02
01
b1111 0
0/
1.
b1010 -
b0 ,
b101 +
0*
b1010 )
b0 (
b101 '
0&
0%
0$
0#
b1111 "
0!
$end
#10
1%
12
1N
1M
1L
1K
0$
1I
1J
1G
1H
13
b11110101 4
b11110101 F
0&
b101 0
b101 Q
0.
1/
b11111010 P
b101 O
0!
b101 "
b101 D
b10 (
b10 ,
b1111 '
b1111 +
b1111 E
#20
0K
0J
0L
0M
02
0N
0H
0I
03
0G
b1111 4
b1111 F
b11111111 0
b11111111 Q
0/
b11111111 P
b0 O
0%
1!
b0 "
b0 D
b100 (
b100 ,
b1111 )
b1111 -
b11110000 '
b11110000 +
b11110000 E
#30
1$
0!
b11111111 "
b11111111 D
b101 (
b101 ,
#40
0I
0J
0K
0L
0M
02
0N
0H
b11111111 0
b11111111 Q
b1010101 4
b1010101 F
b11111111 P
b0 O
0!
b11111111 "
b11111111 D
b110 (
b110 ,
b1010101 )
b1010101 -
b10101010 '
b10101010 +
b10101010 E
#50
1H
1I
1J
1K
0L
0M
02
0N
1G
b1100100 0
b1100100 Q
b1011010 P
b101 O
0!
b11110000 "
b11110000 D
b111 (
b111 ,
b1111 '
b1111 +
b1111 E
#60
0J
0H
0I
b11100110 0
b11100110 Q
0$
b11000100 P
b10001 O
1%
0!
b1001000 "
b1001000 D
b1000 (
b1000 ,
b10010001 '
b10010001 +
b10010001 E
#70
1%
0!
b100010 "
b100010 D
b1001 (
b1001 ,
